filiz/__init__.py
filiz/find_ec_order.py
filiz/find_factors.py
filiz/find_gcd.py
filiz/find_multiplication_of_point.py
filiz/find_point.py
filiz/find_point_binary.py
filiz/find_power_points.py
filiz/find_sum_points.py
filiz-0.0.2.dist-info/METADATA
filiz-0.0.2.dist-info/WHEEL
filiz-0.0.2.dist-info/top_level.txt
filiz-0.0.2.dist-info/RECORD
