Metadata-Version: 2.1
Name: filiz
Version: 0.0.2
Summary: Elliptic Curve Cryptograpy and more...
Home-page: https://github.com/aksoyfiliz/filiz
Author: Filiz Aksoy
Author-email: aksoyfiliz09@gmail.com
License: UNKNOWN
Platform: UNKNOWN
Classifier: Programming Language :: Python :: 3
Classifier: License :: OSI Approved :: MIT License
Classifier: Operating System :: OS Independent
Requires-Python: >=3.6
